shttp/__main__.py
shttp/types.py
shttp_cli-0.1.0.dist-info/entry_points.txt
shttp_cli-0.1.0.dist-info/LICENSE
shttp_cli-0.1.0.dist-info/METADATA
shttp_cli-0.1.0.dist-info/WHEEL
shttp_cli-0.1.0.dist-info/RECORD
