Metadata-Version: 2.1
Name: shttp-cli
Version: 0.1.0
Summary: A command-line HTTP client.
Home-page: https://github.com/interrrp/shttp
License: GPL-3.0-or-later
Author: int
Author-email: int@addictedto.coffee
Requires-Python: >=3.11,<4.0
Classifier: License :: OSI Approved :: GNU General Public License v3 or later (GPLv3+)
Classifier: Programming Language :: Python :: 3
Classifier: Programming Language :: Python :: 3.11
Requires-Dist: requests (>=2.31.0,<3.0.0)
Requires-Dist: typer (>=0.9.0,<0.10.0)
Project-URL: Repository, https://github.com/interrrp/shttp
